codemod_unittest_to_pytest_asserts/__init__.py
codemod_unittest_to_pytest_asserts-1.2.0.dist-info/LICENSE
codemod_unittest_to_pytest_asserts-1.2.0.dist-info/METADATA
codemod_unittest_to_pytest_asserts-1.2.0.dist-info/WHEEL
codemod_unittest_to_pytest_asserts-1.2.0.dist-info/entry_points.txt
codemod_unittest_to_pytest_asserts-1.2.0.dist-info/top_level.txt
codemod_unittest_to_pytest_asserts-1.2.0.dist-info/RECORD
