Metadata-Version: 2.1
Name: codemod-unittest-to-pytest-asserts
Version: 1.2.0
Summary: Codemod to refactor unittest assertions to pytest assertions.
Home-page: https://github.com/hanswilw/codemod-unittest-to-pytest-asserts
Author: Hans-Wilhelm Warlo
Author-email: hw@warlo.no
License: MIT
Platform: UNKNOWN
Classifier: Programming Language :: Python :: 3
Classifier: Programming Language :: Python :: 3.8
Requires-Python: >=3.8
License-File: LICENSE
Requires-Dist: codemod (>=1.0.0)
Requires-Dist: astunparse (>=1.6.2)
